GrayCode/graycode.v
module SRFlipFlop(S, R, clk, reset, Q);
    input S, R, clk, reset;
    output reg Q;

    always @(posedge clk or posedge reset)
        if(reset) Q <= 0;
        else begin
        case ({S,R})
            2'b00 :  Q <= Q;  
            2'b01 :  Q <= 0;
            2'b10 :  Q <= 1;
          endcase 
        end
endmodule

module GrayCodeCounter(clk, reset, out);
    input clk, reset;
    output [3:0] out;

    wire [3:0] Q;
    wire [3:0] S;
    wire [3:0] R;

    assign S[3] = (Q[2] & ~Q[1] & ~Q[0]);
    assign R[3] =(~Q[2] & ~Q[1] & ~Q[0]);

    assign S[2] = (~Q[3] & Q[1] & ~Q[0]);
    assign R[2] = (Q[3] & Q[1] & ~Q[0]);

    assign S[1] = (~Q[3] & ~Q[2] & Q[0]) | (Q[3] & Q[2] & Q[0]);
    assign R[1] = (~Q[3] & Q[2] & Q[0]) | (Q[3] & ~Q[2] & Q[0]);
    
    assign S[0] = (~Q[3] & ~Q[2] & ~Q[1]) | (~Q[3] & Q[2] & Q[1]) | (Q[3] & ~Q[2] & Q[1]) | (Q[3] & Q[2]& ~Q[1]);
    assign R[0] = (~Q[3] & ~Q[2] & Q[1]) | (~Q[3] & Q[2] & ~Q[1]) | (Q[3] & ~Q[2] & ~Q[1]) | (Q[3] & Q[2] & Q[1]);

    SRFlipFlop sr0 (S[0], R[0], clk, reset, Q[0]);
    SRFlipFlop sr1 (S[1], R[1], clk, reset, Q[1]);
    SRFlipFlop sr2 (S[2], R[2], clk, reset, Q[2]);
    SRFlipFlop sr3 (S[3], R[3], clk, reset, Q[3]);

    assign out=Q;
endmodule

GrayCode/tb_graycode.v
module tb_graycode;
    reg clk;
    reg reset;
    wire [3:0] out;
    
    GrayCodeCounter counter(clk, reset, out);

    always #10 clk = ~clk;
    initial
        begin
            $dumpfile("graycode.vcd");
			$dumpvars(0, tb_graycode);
            $monitor($time," %b", out);
            reset <= 1;  
            clk <= 0; 
            repeat (1) @ (posedge clk);  
            reset <= 0;  
            repeat (17) @ (posedge clk);  
            $finish;
        end
endmodule

GrayCode/graycode.vcd
$date
	Mon May 17 22:34:21 2021
$end
$version
	Icarus Verilog
$end
$timescale
	1s
$end
$scope module tb_graycode $end
$var wire 4 ! out [3:0] $end
$var reg 1 " clk $end
$var reg 1 # reset $end
$scope module counter $end
$var wire 1 " clk $end
$var wire 4 $ out [3:0] $end
$var wire 1 # reset $end
$var wire 4 % S [3:0] $end
$var wire 4 & R [3:0] $end
$var wire 4 ' Q [3:0] $end
$scope module sr0 $end
$var wire 1 ( R $end
$var wire 1 ) S $end
$var wire 1 " clk $end
$var wire 1 # reset $end
$var reg 1 * Q $end
$upscope $end
$scope module sr1 $end
$var wire 1 + R $end
$var wire 1 , S $end
$var wire 1 " clk $end
$var wire 1 # reset $end
$var reg 1 - Q $end
$upscope $end
$scope module sr2 $end
$var wire 1 . R $end
$var wire 1 / S $end
$var wire 1 " clk $end
$var wire 1 # reset $end
$var reg 1 0 Q $end
$upscope $end
$scope module sr3 $end
$var wire 1 1 R $end
$var wire 1 2 S $end
$var wire 1 " clk $end
$var wire 1 # reset $end
$var reg 1 3 Q $end
$upscope $end
$upscope $end
$upscope $end
$enddefinitions $end
#0
$dumpvars
03
02
11
00
0/
0.
0-
0,
0+
0*
1)
0(
b0 '
b1000 &
b1 %
b0 $
1#
0"
b0 !
$end
#10
0#
1"
#20
0"
#30
1,
01
b11 %
b0 &
b1 !
b1 $
b1 '
1*
1"
#40
0"
#50
0)
1(
b10 %
b1 &
b11 !
b11 $
b11 '
1-
1"
#60
0"
#70
0,
1/
b100 %
b10 !
b10 $
b10 '
0*
1"
#80
0"
#90
0(
b0 &
1)
b101 %
b110 !
b110 $
b110 '
10
1"
#100
0"
#110
1+
0/
b10 &
b1 %
b111 !
b111 $
b111 '
1*
1"
#120
0"
#130
1(
b11 &
0)
b0 %
b101 !
b101 $
b101 '
0-
1"
#140
0"
#150
0+
12
b1 &
b1000 %
b100 !
b100 $
b100 '
0*
1"
#160
0"
#170
0(
b0 &
1)
b1001 %
b1100 !
b1100 $
b1100 '
13
1"
#180
0"
#190
1,
02
b11 %
b1101 !
b1101 $
b1101 '
1*
1"
#200
0"
#210
0)
1(
b10 %
b1 &
b1111 !
b1111 $
b1111 '
1-
1"
#220
0"
#230
0,
1.
b0 %
b101 &
b1110 !
b1110 $
b1110 '
0*
1"
#240
0"
#250
1)
b1 %
0(
b100 &
b1010 !
b1010 $
b1010 '
00
1"
#260
0"
#270
1+
0.
b10 &
b1011 !
b1011 $
b1011 '
1*
1"
#280
0"
#290
1(
b11 &
0)
b0 %
b1001 !
b1001 $
b1001 '
0-
1"
#300
0"
#310
0+
11
b1001 &
b1000 !
b1000 $
b1000 '
0*
1"
#320
0"
#330
1)
b1 %
0(
b1000 &
b0 !
b0 $
b0 '
03
1"
#340
0"
#350
1,
01
b11 %
b0 &
b1 !
b1 $
b1 '
1*
1"
